python_ramzinex_api/__init__.py
python_ramzinex_api/ramzinex.py
python_ramzinex_api-0.1.15.dist-info/METADATA
python_ramzinex_api-0.1.15.dist-info/WHEEL
python_ramzinex_api-0.1.15.dist-info/top_level.txt
python_ramzinex_api-0.1.15.dist-info/RECORD
